mscxyz/__init__.py
mscxyz/cli.py
mscxyz/export.py
mscxyz/fields.py
mscxyz/lyrics.py
mscxyz/meta.py
mscxyz/rename.py
mscxyz/score.py
mscxyz/settings.py
mscxyz/style.py
mscxyz/style_names.py
mscxyz/utils.py
mscxyz/xml.py
mscxyz-4.0.0.dist-info/LICENSE
mscxyz-4.0.0.dist-info/METADATA
mscxyz-4.0.0.dist-info/WHEEL
mscxyz-4.0.0.dist-info/entry_points.txt
mscxyz-4.0.0.dist-info/RECORD
