Metadata-Version: 2.1
Name: mscxyz
Version: 4.0.0
Summary: A command line tool to manipulate the XML based *.mscX and *.mscZ files of the notation software MuseScore.
Home-page: https://mscxyz.readthedocs.io
Keywords: audio
Author: Josef Friedrich
Author-email: josef@friedrich.rocks
Requires-Python: >=3.10,<4.0
Classifier: Development Status :: 5 - Production/Stable
Classifier: License :: OSI Approved :: MIT License
Classifier: Programming Language :: Python :: 3
Classifier: Programming Language :: Python :: 3.10
Classifier: Programming Language :: Python :: 3.11
Classifier: Programming Language :: Python :: 3.12
Classifier: Programming Language :: Python :: 3.13
Classifier: Programming Language :: Python :: 3 :: Only
Requires-Dist: lxml (>=5.3.0,<6.0.0)
Requires-Dist: lxml-stubs (>=0.5.1,<0.6.0)
Requires-Dist: shtab (>=1.7.1,<2.0.0)
Requires-Dist: termcolor (>=2.5.0,<3.0.0)
Requires-Dist: tmep (>=3.0.0,<4.0.0)
Project-URL: Repository, https://github.com/Josef-Friedrich/mscxyz
